delfile_bydate/__init__.py
delfile_bydate/app.py
delfile_bydate-0.0.7.data/scripts/delfile
delfile_bydate-0.0.7.dist-info/METADATA
delfile_bydate-0.0.7.dist-info/WHEEL
delfile_bydate-0.0.7.dist-info/top_level.txt
delfile_bydate-0.0.7.dist-info/RECORD
