Metadata-Version: 2.1
Name: delfile-bydate
Version: 0.0.7
Summary: Load and Train github issue to model
Home-page: https://github.com/panu00x/LoadIssue
Author: panu00x
Author-email: lewpanu@gmail.com
License: UNKNOWN
Platform: UNKNOWN
Classifier: Programming Language :: Python :: 3
Classifier: License :: OSI Approved :: MIT License
Classifier: Operating System :: OS Independent
Requires-Python: >=3.6
